INSTALL
LICENSE
MANIFEST.in
README.md
setup.py
django_mongokit/__init__.py
django_mongokit/document.py
django_mongokit/shortcut.py
django_mongokit/test_settings.py
django_mongokit/test_settings_django11.py
django_mongokit/tests.py
django_mongokit/version.txt
django_mongokit.egg-info/PKG-INFO
django_mongokit.egg-info/SOURCES.txt
django_mongokit.egg-info/dependency_links.txt
django_mongokit.egg-info/requires.txt
django_mongokit.egg-info/top_level.txt
django_mongokit/forms/__init__.py
django_mongokit/forms/fields.py
django_mongokit/forms/forms.py
django_mongokit/mongodb/__init__.py
django_mongokit/mongodb/base.py