Metadata-Version: 1.0
Name: django-mongokit
Version: 0.2.6
Summary: Bridging Django to MongoDB with the MongoKit ODM
Home-page: https://github.com/peterbe/django-mongokit
Author: Peter Bengtsson
Author-email: mail@peterbe.com
License: UNKNOWN
Platform: UNKNOWN
Classifier: Development Status :: 5 - Production/Stable
Classifier: Environment :: Web Environment
Classifier: Framework :: Django
Classifier: Intended Audience :: Developers
Classifier: License :: OSI Approved :: BSD License
Classifier: Operating System :: OS Independent
Classifier: Programming Language :: Python
Classifier: Topic :: Utilities
